plover_excel_dictionary.py
plover_excel_dictionary-1.0.1.dist-info/METADATA
plover_excel_dictionary-1.0.1.dist-info/WHEEL
plover_excel_dictionary-1.0.1.dist-info/entry_points.txt
plover_excel_dictionary-1.0.1.dist-info/top_level.txt
plover_excel_dictionary-1.0.1.dist-info/zip-safe
plover_excel_dictionary-1.0.1.dist-info/RECORD
