Metadata-Version: 2.1
Name: plover-excel-dictionary
Version: 1.0.1
Summary: Excel dictionaries support for Plover
Home-page: https://github.com/benoit-pierre/plover_excel_dictionary
Author: Benoit Pierre
Author-email: benoit.pierre@gmail.com
License: GNU General Public License v2 or later (GPLv2+)
Keywords: plover plover_plugin
Platform: UNKNOWN
Classifier: Development Status :: 4 - Beta
Classifier: Environment :: Plugins
Classifier: Intended Audience :: End Users/Desktop
Classifier: License :: OSI Approved :: GNU General Public License v2 or later (GPLv2+)
Classifier: Operating System :: OS Independent
Classifier: Programming Language :: Python :: 3
Classifier: Programming Language :: Python :: 3.6
Classifier: Programming Language :: Python :: 3.7
Classifier: Programming Language :: Python :: 3.8
Classifier: Programming Language :: Python :: 3.9
Requires-Python: >=3.6
Requires-Dist: importlib-metadata
Requires-Dist: plover (>=4.0.0.dev9)
Requires-Dist: pyexcel (>=0.4.5)
Requires-Dist: pyexcel-ods (>=0.6.0)
Requires-Dist: pyexcel-xlsx (>=0.3.0)
Provides-Extra: test
Requires-Dist: plover (>=4.0.0.dev10) ; extra == 'test'
Requires-Dist: pytest ; extra == 'test'
